{
  "appInfo" : {
    "build" : "221.5921.27",
    "buildDate" : "2022-06-21T21:03:23.902Z[UTC]",
    "productCode" : "CL",
    "generated" : "2022-10-29T12:21:12.401612Z",
    "os" : "Linux 4.15.0-166-generic",
    "runtime" : "JetBrains s.r.o. 11.0.15 11.0.15+10-b2043.56"
  },
  "runtimeInfo" : {
    "maxMemory" : 2147483648,
    "numberOfProcessors" : 6,
    "maxNumberOfIndexingThreads" : 4,
    "maxSizeOfFileForIntelliSense" : 2560000,
    "maxSizeOfFileForContentLoading" : 20971520
  },
  "projectIndexingHistory" : {
    "projectName" : "u6281556",
    "times" : {
      "indexingReason" : "On refresh of 10 files",
      "scanningType" : "REFRESH",
      "totalUpdatingTime" : 194866598,
      "indexingTime" : 194490000,
      "contentLoadingVisibleTime" : 1161255,
      "creatingIteratorsTime" : 0,
      "scanFilesTime" : 68054,
      "pushPropertiesTime" : 0,
      "indexExtensionsTime" : 0,
      "isAppliedAllValuesSeparately" : true,
      "separateApplyingIndexesVisibleTime" : 3569689,
      "updatingStart" : "2022-10-29T12:21:12.206265Z",
      "updatingEnd" : "2022-10-29T12:21:12.401129Z",
      "totalSuspendedTime" : 0,
      "wasInterrupted" : false
    },
    "fileCount" : {
      "numberOfFileProviders" : 1,
      "numberOfScannedFiles" : 10,
      "numberOfFilesIndexedByInfrastructureExtensionsDuringScan" : 0,
      "numberOfFilesScheduledForIndexingAfterScan" : 10,
      "numberOfFilesIndexedByInfrastructureExtensionsDuringIndexingStage" : 0,
      "numberOfFilesIndexedWithLoadingContent" : 10
    },
    "totalStatsPerFileType" : [ {
      "fileType" : "HTML",
      "partOfTotalProcessingTime" : {
        "part" : 302429290,
        "total" : 369992242
      },
      "partOfTotalContentLoadingTime" : {
        "part" : 972378,
        "total" : 2209604
      },
      "totalNumberOfFiles" : 2,
      "totalFilesSize" : 64513,
      "indexingSpeed" : {
        "totalBytes" : 64513,
        "totalTime" : 302429290
      },
      "biggestContributors" : [ {
        "providerName" : "Refreshed files",
        "numberOfFiles" : 2,
        "totalFilesSize" : 64513,
        "partOfTotalProcessingTimeOfThisFileType" : {
          "part" : 302429290,
          "total" : 302429290
        }
      } ]
    }, {
      "fileType" : "textmate",
      "partOfTotalProcessingTime" : {
        "part" : 57340991,
        "total" : 369992242
      },
      "partOfTotalContentLoadingTime" : {
        "part" : 769147,
        "total" : 2209604
      },
      "totalNumberOfFiles" : 1,
      "totalFilesSize" : 785790,
      "indexingSpeed" : {
        "totalBytes" : 785790,
        "totalTime" : 57340991
      },
      "biggestContributors" : [ {
        "providerName" : "Refreshed files",
        "numberOfFiles" : 1,
        "totalFilesSize" : 785790,
        "partOfTotalProcessingTimeOfThisFileType" : {
          "part" : 57340991,
          "total" : 57340991
        }
      } ]
    }, {
      "fileType" : "JSON",
      "partOfTotalProcessingTime" : {
        "part" : 9602743,
        "total" : 369992242
      },
      "partOfTotalContentLoadingTime" : {
        "part" : 380884,
        "total" : 2209604
      },
      "totalNumberOfFiles" : 2,
      "totalFilesSize" : 33936,
      "indexingSpeed" : {
        "totalBytes" : 33936,
        "totalTime" : 9602743
      },
      "biggestContributors" : [ {
        "providerName" : "Refreshed files",
        "numberOfFiles" : 2,
        "totalFilesSize" : 33936,
        "partOfTotalProcessingTimeOfThisFileType" : {
          "part" : 9602743,
          "total" : 9602743
        }
      } ]
    }, {
      "fileType" : "UNKNOWN",
      "partOfTotalProcessingTime" : {
        "part" : 619218,
        "total" : 369992242
      },
      "partOfTotalContentLoadingTime" : {
        "part" : 87195,
        "total" : 2209604
      },
      "totalNumberOfFiles" : 5,
      "totalFilesSize" : 0,
      "indexingSpeed" : {
        "totalBytes" : 0,
        "totalTime" : 619218
      },
      "biggestContributors" : [ {
        "providerName" : "Refreshed files",
        "numberOfFiles" : 5,
        "totalFilesSize" : 0,
        "partOfTotalProcessingTimeOfThisFileType" : {
          "part" : 619218,
          "total" : 619218
        }
      } ]
    } ],
    "totalStatsPerIndexer" : [ {
      "indexId" : "fileIncludes",
      "partOfTotalIndexingTime" : {
        "part" : 122402693,
        "total" : 340393199
      },
      "totalNumberOfFiles" : 2,
      "totalNumberOfFilesIndexedByExtensions" : 0,
      "totalFilesSize" : 64513,
      "indexingSpeed" : {
        "totalBytes" : 64513,
        "totalTime" : 122402693
      },
      "snapshotInputMappingStats" : {
        "totalRequests" : 0,
        "totalMisses" : 0,
        "totalHits" : 0
      }
    }, {
      "indexId" : "css.template.selectors",
      "partOfTotalIndexingTime" : {
        "part" : 58387208,
        "total" : 340393199
      },
      "totalNumberOfFiles" : 2,
      "totalNumberOfFilesIndexedByExtensions" : 0,
      "totalFilesSize" : 64513,
      "indexingSpeed" : {
        "totalBytes" : 64513,
        "totalTime" : 58387208
      },
      "snapshotInputMappingStats" : {
        "totalRequests" : 0,
        "totalMisses" : 0,
        "totalHits" : 0
      }
    }, {
      "indexId" : "IdIndex",
      "partOfTotalIndexingTime" : {
        "part" : 46677864,
        "total" : 340393199
      },
      "totalNumberOfFiles" : 5,
      "totalNumberOfFilesIndexedByExtensions" : 0,
      "totalFilesSize" : 884239,
      "indexingSpeed" : {
        "totalBytes" : 884239,
        "totalTime" : 46677864
      },
      "snapshotInputMappingStats" : {
        "totalRequests" : 0,
        "totalMisses" : 0,
        "totalHits" : 0
      }
    }, {
      "indexId" : "js.custom.single.entry.index",
      "partOfTotalIndexingTime" : {
        "part" : 41876205,
        "total" : 340393199
      },
      "totalNumberOfFiles" : 2,
      "totalNumberOfFilesIndexedByExtensions" : 0,
      "totalFilesSize" : 64513,
      "indexingSpeed" : {
        "totalBytes" : 64513,
        "totalTime" : 41876205
      },
      "snapshotInputMappingStats" : {
        "totalRequests" : 0,
        "totalMisses" : 0,
        "totalHits" : 0
      }
    }, {
      "indexId" : "Trigram.Index",
      "partOfTotalIndexingTime" : {
        "part" : 18485792,
        "total" : 340393199
      },
      "totalNumberOfFiles" : 5,
      "totalNumberOfFilesIndexedByExtensions" : 0,
      "totalFilesSize" : 884239,
      "indexingSpeed" : {
        "totalBytes" : 884239,
        "totalTime" : 18485792
      },
      "snapshotInputMappingStats" : {
        "totalRequests" : 0,
        "totalMisses" : 0,
        "totalHits" : 0
      }
    }, {
      "indexId" : "CssIndex",
      "partOfTotalIndexingTime" : {
        "part" : 15775423,
        "total" : 340393199
      },
      "totalNumberOfFiles" : 2,
      "totalNumberOfFilesIndexedByExtensions" : 0,
      "totalFilesSize" : 64513,
      "indexingSpeed" : {
        "totalBytes" : 64513,
        "totalTime" : 15775423
      },
      "snapshotInputMappingStats" : {
        "totalRequests" : 0,
        "totalMisses" : 0,
        "totalHits" : 0
      }
    }, {
      "indexId" : "html5.custom.attributes.index",
      "partOfTotalIndexingTime" : {
        "part" : 13103727,
        "total" : 340393199
      },
      "totalNumberOfFiles" : 2,
      "totalNumberOfFilesIndexedByExtensions" : 0,
      "totalFilesSize" : 64513,
      "indexingSpeed" : {
        "totalBytes" : 64513,
        "totalTime" : 13103727
      },
      "snapshotInputMappingStats" : {
        "totalRequests" : 0,
        "totalMisses" : 0,
        "totalHits" : 0
      }
    }, {
      "indexId" : "HtmlTagIdIndex",
      "partOfTotalIndexingTime" : {
        "part" : 9243461,
        "total" : 340393199
      },
      "totalNumberOfFiles" : 2,
      "totalNumberOfFilesIndexedByExtensions" : 0,
      "totalFilesSize" : 64513,
      "indexingSpeed" : {
        "totalBytes" : 64513,
        "totalTime" : 9243461
      },
      "snapshotInputMappingStats" : {
        "totalRequests" : 0,
        "totalMisses" : 0,
        "totalHits" : 0
      }
    }, {
      "indexId" : "HtmlScriptSrcIndex",
      "partOfTotalIndexingTime" : {
        "part" : 9068689,
        "total" : 340393199
      },
      "totalNumberOfFiles" : 2,
      "totalNumberOfFilesIndexedByExtensions" : 0,
      "totalFilesSize" : 64513,
      "indexingSpeed" : {
        "totalBytes" : 64513,
        "totalTime" : 9068689
      },
      "snapshotInputMappingStats" : {
        "totalRequests" : 0,
        "totalMisses" : 0,
        "totalHits" : 0
      }
    }, {
      "indexId" : "Stubs",
      "partOfTotalIndexingTime" : {
        "part" : 4452498,
        "total" : 340393199
      },
      "totalNumberOfFiles" : 2,
      "totalNumberOfFilesIndexedByExtensions" : 0,
      "totalFilesSize" : 64513,
      "indexingSpeed" : {
        "totalBytes" : 64513,
        "totalTime" : 4452498
      },
      "snapshotInputMappingStats" : {
        "totalRequests" : 0,
        "totalMisses" : 0,
        "totalHits" : 0
      }
    }, {
      "indexId" : "json.file.root.values",
      "partOfTotalIndexingTime" : {
        "part" : 911914,
        "total" : 340393199
      },
      "totalNumberOfFiles" : 2,
      "totalNumberOfFilesIndexedByExtensions" : 0,
      "totalFilesSize" : 33936,
      "indexingSpeed" : {
        "totalBytes" : 33936,
        "totalTime" : 911914
      },
      "snapshotInputMappingStats" : {
        "totalRequests" : 0,
        "totalMisses" : 0,
        "totalHits" : 0
      }
    }, {
      "indexId" : "js.implicit.elements.index",
      "partOfTotalIndexingTime" : {
        "part" : 7725,
        "total" : 340393199
      },
      "totalNumberOfFiles" : 2,
      "totalNumberOfFilesIndexedByExtensions" : 0,
      "totalFilesSize" : 64513,
      "indexingSpeed" : {
        "totalBytes" : 64513,
        "totalTime" : 7725
      },
      "snapshotInputMappingStats" : {
        "totalRequests" : 0,
        "totalMisses" : 0,
        "totalHits" : 0
      }
    } ],
    "scanningStatistics" : [ {
      "providerName" : "Refreshed files",
      "numberOfScannedFiles" : 10,
      "numberOfSkippedFiles" : 0,
      "numberOfFilesForIndexing" : 10,
      "numberOfFilesFullyIndexedByInfrastructureExtensions" : 0,
      "filesFullyIndexedByInfrastructureExtensions" : [ ],
      "statusTime" : 0,
      "scanningTime" : 68054,
      "timeProcessingUpToDateFiles" : 0,
      "timeUpdatingContentLessIndexes" : 0,
      "timeIndexingWithoutContent" : 0,
      "roots" : [ "Not collected for refresh" ]
    } ],
    "fileProviderStatistics" : [ {
      "providerName" : "Refreshed files",
      "totalNumberOfIndexedFiles" : 10,
      "totalNumberOfFilesFullyIndexedByExtensions" : 0,
      "totalIndexingVisibleTime" : 194449120,
      "contentLoadingVisibleTime" : 1161255,
      "numberOfTooLargeForIndexingFiles" : 0,
      "slowIndexedFiles" : [ ],
      "filesFullyIndexedByExtensions" : [ ],
      "isAppliedAllValuesSeparately" : true,
      "separateApplyingIndexesVisibleTime" : 3569689
    } ],
    "visibleTimeToAllThreadTimeRatio" : 0.5255491816501385
  }
}