{
  "appInfo" : {
    "build" : "221.5921.27",
    "buildDate" : "2022-06-21T21:03:23.902Z[UTC]",
    "productCode" : "CL",
    "generated" : "2022-10-29T11:41:01.90682Z",
    "os" : "Linux 4.15.0-166-generic",
    "runtime" : "JetBrains s.r.o. 11.0.15 11.0.15+10-b2043.56"
  },
  "runtimeInfo" : {
    "maxMemory" : 2147483648,
    "numberOfProcessors" : 6,
    "maxNumberOfIndexingThreads" : 4,
    "maxSizeOfFileForIntelliSense" : 2560000,
    "maxSizeOfFileForContentLoading" : 20971520
  },
  "projectIndexingHistory" : {
    "projectName" : "u6281556",
    "times" : {
      "indexingReason" : "On refresh of 12 files",
      "scanningType" : "REFRESH",
      "totalUpdatingTime" : 100823738,
      "indexingTime" : 100410000,
      "contentLoadingVisibleTime" : 1012009,
      "creatingIteratorsTime" : 0,
      "scanFilesTime" : 547358,
      "pushPropertiesTime" : 0,
      "indexExtensionsTime" : 0,
      "isAppliedAllValuesSeparately" : true,
      "separateApplyingIndexesVisibleTime" : 3691405,
      "updatingStart" : "2022-10-29T11:41:01.805334Z",
      "updatingEnd" : "2022-10-29T11:41:01.906154Z",
      "totalSuspendedTime" : 0,
      "wasInterrupted" : false
    },
    "fileCount" : {
      "numberOfFileProviders" : 1,
      "numberOfScannedFiles" : 12,
      "numberOfFilesIndexedByInfrastructureExtensionsDuringScan" : 0,
      "numberOfFilesScheduledForIndexingAfterScan" : 12,
      "numberOfFilesIndexedByInfrastructureExtensionsDuringIndexingStage" : 0,
      "numberOfFilesIndexedWithLoadingContent" : 12
    },
    "totalStatsPerFileType" : [ {
      "fileType" : "HTML",
      "partOfTotalProcessingTime" : {
        "part" : 147395589,
        "total" : 178916504
      },
      "partOfTotalContentLoadingTime" : {
        "part" : 1056707,
        "total" : 1804118
      },
      "totalNumberOfFiles" : 2,
      "totalFilesSize" : 49404,
      "indexingSpeed" : {
        "totalBytes" : 49404,
        "totalTime" : 147395589
      },
      "biggestContributors" : [ {
        "providerName" : "Refreshed files",
        "numberOfFiles" : 2,
        "totalFilesSize" : 49404,
        "partOfTotalProcessingTimeOfThisFileType" : {
          "part" : 147395589,
          "total" : 147395589
        }
      } ]
    }, {
      "fileType" : "JSON",
      "partOfTotalProcessingTime" : {
        "part" : 13555207,
        "total" : 178916504
      },
      "partOfTotalContentLoadingTime" : {
        "part" : 441103,
        "total" : 1804118
      },
      "totalNumberOfFiles" : 2,
      "totalFilesSize" : 22565,
      "indexingSpeed" : {
        "totalBytes" : 22565,
        "totalTime" : 13555207
      },
      "biggestContributors" : [ {
        "providerName" : "Refreshed files",
        "numberOfFiles" : 2,
        "totalFilesSize" : 22565,
        "partOfTotalProcessingTimeOfThisFileType" : {
          "part" : 13555207,
          "total" : 13555207
        }
      } ]
    }, {
      "fileType" : "AUTO_DETECTED",
      "partOfTotalProcessingTime" : {
        "part" : 13463759,
        "total" : 178916504
      },
      "partOfTotalContentLoadingTime" : {
        "part" : 59426,
        "total" : 1804118
      },
      "totalNumberOfFiles" : 1,
      "totalFilesSize" : 0,
      "indexingSpeed" : {
        "totalBytes" : 0,
        "totalTime" : 13463759
      },
      "biggestContributors" : [ {
        "providerName" : "Refreshed files",
        "numberOfFiles" : 1,
        "totalFilesSize" : 0,
        "partOfTotalProcessingTimeOfThisFileType" : {
          "part" : 13463759,
          "total" : 13463759
        }
      } ]
    }, {
      "fileType" : "UNKNOWN",
      "partOfTotalProcessingTime" : {
        "part" : 3620429,
        "total" : 178916504
      },
      "partOfTotalContentLoadingTime" : {
        "part" : 123517,
        "total" : 1804118
      },
      "totalNumberOfFiles" : 6,
      "totalFilesSize" : 0,
      "indexingSpeed" : {
        "totalBytes" : 0,
        "totalTime" : 3620429
      },
      "biggestContributors" : [ {
        "providerName" : "Refreshed files",
        "numberOfFiles" : 6,
        "totalFilesSize" : 0,
        "partOfTotalProcessingTimeOfThisFileType" : {
          "part" : 3620429,
          "total" : 3620429
        }
      } ]
    }, {
      "fileType" : "textmate",
      "partOfTotalProcessingTime" : {
        "part" : 881520,
        "total" : 178916504
      },
      "partOfTotalContentLoadingTime" : {
        "part" : 123365,
        "total" : 1804118
      },
      "totalNumberOfFiles" : 1,
      "totalFilesSize" : 73,
      "indexingSpeed" : {
        "totalBytes" : 73,
        "totalTime" : 881520
      },
      "biggestContributors" : [ {
        "providerName" : "Refreshed files",
        "numberOfFiles" : 1,
        "totalFilesSize" : 73,
        "partOfTotalProcessingTimeOfThisFileType" : {
          "part" : 881520,
          "total" : 881520
        }
      } ]
    } ],
    "totalStatsPerIndexer" : [ {
      "indexId" : "fileIncludes",
      "partOfTotalIndexingTime" : {
        "part" : 60206192,
        "total" : 152621235
      },
      "totalNumberOfFiles" : 2,
      "totalNumberOfFilesIndexedByExtensions" : 0,
      "totalFilesSize" : 49404,
      "indexingSpeed" : {
        "totalBytes" : 49404,
        "totalTime" : 60206192
      },
      "snapshotInputMappingStats" : {
        "totalRequests" : 0,
        "totalMisses" : 0,
        "totalHits" : 0
      }
    }, {
      "indexId" : "IdIndex",
      "partOfTotalIndexingTime" : {
        "part" : 15357393,
        "total" : 152621235
      },
      "totalNumberOfFiles" : 5,
      "totalNumberOfFilesIndexedByExtensions" : 0,
      "totalFilesSize" : 72042,
      "indexingSpeed" : {
        "totalBytes" : 72042,
        "totalTime" : 15357393
      },
      "snapshotInputMappingStats" : {
        "totalRequests" : 0,
        "totalMisses" : 0,
        "totalHits" : 0
      }
    }, {
      "indexId" : "CssIndex",
      "partOfTotalIndexingTime" : {
        "part" : 12448656,
        "total" : 152621235
      },
      "totalNumberOfFiles" : 2,
      "totalNumberOfFilesIndexedByExtensions" : 0,
      "totalFilesSize" : 49404,
      "indexingSpeed" : {
        "totalBytes" : 49404,
        "totalTime" : 12448656
      },
      "snapshotInputMappingStats" : {
        "totalRequests" : 0,
        "totalMisses" : 0,
        "totalHits" : 0
      }
    }, {
      "indexId" : "js.custom.single.entry.index",
      "partOfTotalIndexingTime" : {
        "part" : 12375317,
        "total" : 152621235
      },
      "totalNumberOfFiles" : 2,
      "totalNumberOfFilesIndexedByExtensions" : 0,
      "totalFilesSize" : 49404,
      "indexingSpeed" : {
        "totalBytes" : 49404,
        "totalTime" : 12375317
      },
      "snapshotInputMappingStats" : {
        "totalRequests" : 0,
        "totalMisses" : 0,
        "totalHits" : 0
      }
    }, {
      "indexId" : "css.template.selectors",
      "partOfTotalIndexingTime" : {
        "part" : 11367204,
        "total" : 152621235
      },
      "totalNumberOfFiles" : 2,
      "totalNumberOfFilesIndexedByExtensions" : 0,
      "totalFilesSize" : 49404,
      "indexingSpeed" : {
        "totalBytes" : 49404,
        "totalTime" : 11367204
      },
      "snapshotInputMappingStats" : {
        "totalRequests" : 0,
        "totalMisses" : 0,
        "totalHits" : 0
      }
    }, {
      "indexId" : "Trigram.Index",
      "partOfTotalIndexingTime" : {
        "part" : 10728249,
        "total" : 152621235
      },
      "totalNumberOfFiles" : 6,
      "totalNumberOfFilesIndexedByExtensions" : 0,
      "totalFilesSize" : 72042,
      "indexingSpeed" : {
        "totalBytes" : 72042,
        "totalTime" : 10728249
      },
      "snapshotInputMappingStats" : {
        "totalRequests" : 0,
        "totalMisses" : 0,
        "totalHits" : 0
      }
    }, {
      "indexId" : "html5.custom.attributes.index",
      "partOfTotalIndexingTime" : {
        "part" : 10375703,
        "total" : 152621235
      },
      "totalNumberOfFiles" : 2,
      "totalNumberOfFilesIndexedByExtensions" : 0,
      "totalFilesSize" : 49404,
      "indexingSpeed" : {
        "totalBytes" : 49404,
        "totalTime" : 10375703
      },
      "snapshotInputMappingStats" : {
        "totalRequests" : 0,
        "totalMisses" : 0,
        "totalHits" : 0
      }
    }, {
      "indexId" : "HtmlTagIdIndex",
      "partOfTotalIndexingTime" : {
        "part" : 7036798,
        "total" : 152621235
      },
      "totalNumberOfFiles" : 2,
      "totalNumberOfFilesIndexedByExtensions" : 0,
      "totalFilesSize" : 49404,
      "indexingSpeed" : {
        "totalBytes" : 49404,
        "totalTime" : 7036798
      },
      "snapshotInputMappingStats" : {
        "totalRequests" : 0,
        "totalMisses" : 0,
        "totalHits" : 0
      }
    }, {
      "indexId" : "HtmlScriptSrcIndex",
      "partOfTotalIndexingTime" : {
        "part" : 6926945,
        "total" : 152621235
      },
      "totalNumberOfFiles" : 2,
      "totalNumberOfFilesIndexedByExtensions" : 0,
      "totalFilesSize" : 49404,
      "indexingSpeed" : {
        "totalBytes" : 49404,
        "totalTime" : 6926945
      },
      "snapshotInputMappingStats" : {
        "totalRequests" : 0,
        "totalMisses" : 0,
        "totalHits" : 0
      }
    }, {
      "indexId" : "Stubs",
      "partOfTotalIndexingTime" : {
        "part" : 4863218,
        "total" : 152621235
      },
      "totalNumberOfFiles" : 2,
      "totalNumberOfFilesIndexedByExtensions" : 0,
      "totalFilesSize" : 49404,
      "indexingSpeed" : {
        "totalBytes" : 49404,
        "totalTime" : 4863218
      },
      "snapshotInputMappingStats" : {
        "totalRequests" : 0,
        "totalMisses" : 0,
        "totalHits" : 0
      }
    }, {
      "indexId" : "json.file.root.values",
      "partOfTotalIndexingTime" : {
        "part" : 929551,
        "total" : 152621235
      },
      "totalNumberOfFiles" : 2,
      "totalNumberOfFilesIndexedByExtensions" : 0,
      "totalFilesSize" : 22565,
      "indexingSpeed" : {
        "totalBytes" : 22565,
        "totalTime" : 929551
      },
      "snapshotInputMappingStats" : {
        "totalRequests" : 0,
        "totalMisses" : 0,
        "totalHits" : 0
      }
    }, {
      "indexId" : "js.implicit.elements.index",
      "partOfTotalIndexingTime" : {
        "part" : 6009,
        "total" : 152621235
      },
      "totalNumberOfFiles" : 2,
      "totalNumberOfFilesIndexedByExtensions" : 0,
      "totalFilesSize" : 49404,
      "indexingSpeed" : {
        "totalBytes" : 49404,
        "totalTime" : 6009
      },
      "snapshotInputMappingStats" : {
        "totalRequests" : 0,
        "totalMisses" : 0,
        "totalHits" : 0
      }
    } ],
    "scanningStatistics" : [ {
      "providerName" : "Refreshed files",
      "numberOfScannedFiles" : 12,
      "numberOfSkippedFiles" : 0,
      "numberOfFilesForIndexing" : 12,
      "numberOfFilesFullyIndexedByInfrastructureExtensions" : 0,
      "filesFullyIndexedByInfrastructureExtensions" : [ ],
      "statusTime" : 0,
      "scanningTime" : 547358,
      "timeProcessingUpToDateFiles" : 0,
      "timeUpdatingContentLessIndexes" : 0,
      "timeIndexingWithoutContent" : 0,
      "roots" : [ "Not collected for refresh" ]
    } ],
    "fileProviderStatistics" : [ {
      "providerName" : "Refreshed files",
      "totalNumberOfIndexedFiles" : 12,
      "totalNumberOfFilesFullyIndexedByExtensions" : 0,
      "totalIndexingVisibleTime" : 100362178,
      "contentLoadingVisibleTime" : 1012009,
      "numberOfTooLargeForIndexingFiles" : 0,
      "slowIndexedFiles" : [ ],
      "filesFullyIndexedByExtensions" : [ ],
      "isAppliedAllValuesSeparately" : true,
      "separateApplyingIndexesVisibleTime" : 3691405
    } ],
    "visibleTimeToAllThreadTimeRatio" : 0.5609442156325612
  }
}